[
    [
        {"opacity": 100},
        {"fill": [235, 116, 73]},
        {"stroke": [35, 31, 32]},
        {"strokeWidth": 2},
        {"line": [1062, -4752, 1081, -4641]},
        {"line": [1081, -4641, 1204, -4641]},
        {"line": [1204, -4641, 1204, -4752]},
        {"line": [1204, -4752, 1062, -4752]}
    ],
    [
        {"opacity": 100},
        {"fill": [235, 116, 73]},
        {"stroke": [35, 31, 32]},
        {"strokeWidth": 2},
        {"line": [1097, -4530, 1204, -4530]},
        {"line": [1204, -4530, 1204, -4641]},
        {"line": [1204, -4641, 1081, -4641]},
        {"line": [1081, -4641, 1097, -4530]}
    ],
    [
        {"opacity": 100},
        {"fill": [235, 116, 73]},
        {"stroke": [35, 31, 32]},
        {"strokeWidth": 2},
        {"line": [1076, -4419, 1204, -4419]},
        {"line": [1204, -4419, 1204, -4530]},
        {"line": [1204, -4530, 1097, -4530]},
        {"line": [1097, -4530, 1076, -4419]}
    ],
    [
        {"opacity": 100},
        {"fill": [235, 116, 73]},
        {"stroke": [35, 31, 32]},
        {"strokeWidth": 2},
        {"line": [1050, -4308, 1204, -4308]},
        {"line": [1204, -4308, 1204, -4419]},
        {"line": [1204, -4419, 1076, -4419]},
        {"line": [1076, -4419, 1050, -4308]}
    ],
    [
        {"opacity": 100},
        {"fill": [235, 116, 73]},
        {"stroke": [35, 31, 32]},
        {"strokeWidth": 2},
        {"line": [1060, -4197, 1204, -4197]},
        {"line": [1204, -4197, 1204, -4308]},
        {"line": [1204, -4308, 1050, -4308]},
        {"line": [1050, -4308, 1060, -4197]}
    ],
    [
        {"opacity": 100},
        {"fill": [235, 116, 73]},
        {"stroke": [35, 31, 32]},
        {"strokeWidth": 2},
        {"line": [1081, -4086, 1204, -4086]},
        {"line": [1204, -4086, 1204, -4197]},
        {"line": [1204, -4197, 1060, -4197]},
        {"line": [1060, -4197, 1081, -4086]}
    ],
    [
        {"opacity": 100},
        {"fill": [235, 116, 73]},
        {"stroke": [35, 31, 32]},
        {"strokeWidth": 2},
        {"line": [1109, -3975, 1204, -3975]},
        {"line": [1204, -3975, 1204, -4086]},
        {"line": [1204, -4086, 1081, -4086]},
        {"line": [1081, -4086, 1109, -3975]}
    ],
    [
        {"opacity": 100},
        {"fill": [235, 116, 73]},
        {"stroke": [35, 31, 32]},
        {"strokeWidth": 2},
        {"line": [1130, -3864, 1204, -3864]},
        {"line": [1204, -3864, 1204, -3975]},
        {"line": [1204, -3975, 1109, -3975]},
        {"line": [1109, -3975, 1130, -3864]}
    ],
    [
        {"opacity": 100},
        {"fill": [235, 116, 73]},
        {"stroke": [35, 31, 32]},
        {"strokeWidth": 2},
        {"line": [1117, -3753, 1204, -3753]},
        {"line": [1204, -3753, 1204, -3864]},
        {"line": [1204, -3864, 1130, -3864]},
        {"line": [1130, -3864, 1117, -3753]}
    ],
    [
        {"opacity": 100},
        {"fill": [235, 116, 73]},
        {"stroke": [35, 31, 32]},
        {"strokeWidth": 2},
        {"line": [1145, -3642, 1204, -3642]},
        {"line": [1204, -3642, 1204, -3753]},
        {"line": [1204, -3753, 1117, -3753]},
        {"line": [1117, -3753, 1145, -3642]}
    ],
    [
        {"opacity": 100},
        {"fill": [235, 116, 73]},
        {"stroke": [35, 31, 32]},
        {"strokeWidth": 2},
        {"line": [1125, -3531, 1204, -3531]},
        {"line": [1204, -3531, 1204, -3642]},
        {"line": [1204, -3642, 1145, -3642]},
        {"line": [1145, -3642, 1125, -3531]}
    ],
    [
        {"opacity": 100},
        {"fill": [235, 116, 73]},
        {"stroke": [35, 31, 32]},
        {"strokeWidth": 2},
        {"line": [1075, -3420, 1204, -3420]},
        {"line": [1204, -3420, 1204, -3531]},
        {"line": [1204, -3531, 1125, -3531]},
        {"line": [1125, -3531, 1075, -3420]}
    ],
    [
        {"opacity": 100},
        {"fill": [235, 116, 73]},
        {"stroke": [35, 31, 32]},
        {"strokeWidth": 2},
        {"line": [1045, -3309, 1204, -3309]},
        {"line": [1204, -3309, 1204, -3420]},
        {"line": [1204, -3420, 1075, -3420]},
        {"line": [1075, -3420, 1045, -3309]}
    ],
    [
        {"opacity": 100},
        {"fill": [235, 116, 73]},
        {"stroke": [35, 31, 32]},
        {"strokeWidth": 2},
        {"line": [1016, -3198, 1204, -3198]},
        {"line": [1204, -3198, 1204, -3309]},
        {"line": [1204, -3309, 1045, -3309]},
        {"line": [1045, -3309, 1016, -3198]}
    ],
    [
        {"opacity": 100},
        {"fill": [235, 116, 73]},
        {"stroke": [35, 31, 32]},
        {"strokeWidth": 2},
        {"line": [967, -3087, 1204, -3087]},
        {"line": [1204, -3087, 1204, -3198]},
        {"line": [1204, -3198, 1016, -3198]},
        {"line": [1016, -3198, 967, -3087]}
    ],
    [
        {"opacity": 100},
        {"fill": [235, 116, 73]},
        {"stroke": [35, 31, 32]},
        {"strokeWidth": 2},
        {"line": [936, -2976, 1204, -2976]},
        {"line": [1204, -2976, 1204, -3087]},
        {"line": [1204, -3087, 967, -3087]},
        {"line": [967, -3087, 936, -2976]}
    ],
    [
        {"opacity": 100},
        {"fill": [235, 116, 73]},
        {"stroke": [35, 31, 32]},
        {"strokeWidth": 2},
        {"line": [982, -2865, 1204, -2865]},
        {"line": [1204, -2865, 1204, -2976]},
        {"line": [1204, -2976, 936, -2976]},
        {"line": [936, -2976, 982, -2865]}
    ],
    [
        {"opacity": 100},
        {"fill": [235, 116, 73]},
        {"stroke": [35, 31, 32]},
        {"strokeWidth": 2},
        {"line": [1013, -2754, 1204, -2754]},
        {"line": [1204, -2754, 1204, -2865]},
        {"line": [1204, -2865, 982, -2865]},
        {"line": [982, -2865, 1013, -2754]}
    ],
    [
        {"opacity": 100},
        {"fill": [235, 116, 73]},
        {"stroke": [35, 31, 32]},
        {"strokeWidth": 2},
        {"line": [1038, -2643, 1204, -2643]},
        {"line": [1204, -2643, 1204, -2754]},
        {"line": [1204, -2754, 1013, -2754]},
        {"line": [1013, -2754, 1038, -2643]}
    ],
    [
        {"opacity": 100},
        {"fill": [235, 116, 73]},
        {"stroke": [35, 31, 32]},
        {"strokeWidth": 2},
        {"line": [1038, -2532, 1204, -2532]},
        {"line": [1204, -2532, 1204, -2643]},
        {"line": [1204, -2643, 1038, -2643]},
        {"line": [1038, -2643, 1038, -2532]}
    ],
    [
        {"opacity": 100},
        {"fill": [235, 116, 73]},
        {"stroke": [35, 31, 32]},
        {"strokeWidth": 2},
        {"line": [1038, -2421, 1204, -2421]},
        {"line": [1204, -2421, 1204, -2532]},
        {"line": [1204, -2532, 1038, -2532]},
        {"line": [1038, -2532, 1038, -2421]}
    ],
    [
        {"opacity": 100},
        {"fill": [235, 116, 73]},
        {"stroke": [35, 31, 32]},
        {"strokeWidth": 2},
        {"line": [1042, -2310, 1204, -2310]},
        {"line": [1204, -2310, 1204, -2421]},
        {"line": [1204, -2421, 1038, -2421]},
        {"line": [1038, -2421, 1042, -2310]}
    ],
    [
        {"opacity": 100},
        {"fill": [235, 116, 73]},
        {"stroke": [35, 31, 32]},
        {"strokeWidth": 2},
        {"line": [1055, -2199, 1204, -2199]},
        {"line": [1204, -2199, 1204, -2310]},
        {"line": [1204, -2310, 1042, -2310]},
        {"line": [1042, -2310, 1055, -2199]}
    ],
    [
        {"opacity": 100},
        {"fill": [235, 116, 73]},
        {"stroke": [35, 31, 32]},
        {"strokeWidth": 2},
        {"line": [1026, -2088, 1204, -2088]},
        {"line": [1204, -2088, 1204, -2199]},
        {"line": [1204, -2199, 1055, -2199]},
        {"line": [1055, -2199, 1026, -2088]}
    ],
    [
        {"opacity": 100},
        {"fill": [235, 116, 73]},
        {"stroke": [35, 31, 32]},
        {"strokeWidth": 2},
        {"line": [984, -1977, 1204, -1977]},
        {"line": [1204, -1977, 1204, -2088]},
        {"line": [1204, -2088, 1026, -2088]},
        {"line": [1026, -2088, 984, -1977]}
    ],
    [
        {"opacity": 100},
        {"fill": [235, 116, 73]},
        {"stroke": [35, 31, 32]},
        {"strokeWidth": 2},
        {"line": [974, -1866, 1204, -1866]},
        {"line": [1204, -1866, 1204, -1977]},
        {"line": [1204, -1977, 984, -1977]},
        {"line": [984, -1977, 974, -1866]}
    ],
    [
        {"opacity": 100},
        {"fill": [235, 116, 73]},
        {"stroke": [35, 31, 32]},
        {"strokeWidth": 2},
        {"line": [989, -1756, 1204, -1756]},
        {"line": [1204, -1756, 1204, -1866]},
        {"line": [1204, -1866, 974, -1866]},
        {"line": [974, -1866, 989, -1756]}
    ],
    [
        {"opacity": 100},
        {"fill": [235, 116, 73]},
        {"stroke": [35, 31, 32]},
        {"strokeWidth": 2},
        {"line": [1015, -1645, 1204, -1645]},
        {"line": [1204, -1645, 1204, -1756]},
        {"line": [1204, -1756, 989, -1756]},
        {"line": [989, -1756, 1015, -1645]}
    ],
    [
        {"opacity": 100},
        {"fill": [235, 116, 73]},
        {"stroke": [35, 31, 32]},
        {"strokeWidth": 2},
        {"line": [1000, -1534, 1204, -1534]},
        {"line": [1204, -1534, 1204, -1645]},
        {"line": [1204, -1645, 1015, -1645]},
        {"line": [1015, -1645, 1000, -1534]}
    ],
    [
        {"opacity": 100},
        {"fill": [235, 116, 73]},
        {"stroke": [35, 31, 32]},
        {"strokeWidth": 2},
        {"line": [1006, -1423, 1204, -1423]},
        {"line": [1204, -1423, 1204, -1534]},
        {"line": [1204, -1534, 1000, -1534]},
        {"line": [1000, -1534, 1006, -1423]}
    ],
    [
        {"opacity": 100},
        {"fill": [235, 116, 73]},
        {"stroke": [35, 31, 32]},
        {"strokeWidth": 2},
        {"line": [998, -1312, 1204, -1312]},
        {"line": [1204, -1312, 1204, -1423]},
        {"line": [1204, -1423, 1006, -1423]},
        {"line": [1006, -1423, 998, -1312]}
    ],
    [
        {"opacity": 100},
        {"fill": [235, 116, 73]},
        {"stroke": [35, 31, 32]},
        {"strokeWidth": 2},
        {"line": [1017, -1201, 1204, -1201]},
        {"line": [1204, -1201, 1204, -1312]},
        {"line": [1204, -1312, 998, -1312]},
        {"line": [998, -1312, 1017, -1201]}
    ],
    [
        {"opacity": 100},
        {"fill": [235, 116, 73]},
        {"stroke": [35, 31, 32]},
        {"strokeWidth": 2},
        {"line": [1052, -1090, 1204, -1090]},
        {"line": [1204, -1090, 1204, -1201]},
        {"line": [1204, -1201, 1017, -1201]},
        {"line": [1017, -1201, 1052, -1090]}
    ],
    [
        {"opacity": 100},
        {"fill": [235, 116, 73]},
        {"stroke": [35, 31, 32]},
        {"strokeWidth": 2},
        {"line": [1041, -979, 1204, -979]},
        {"line": [1204, -979, 1204, -1090]},
        {"line": [1204, -1090, 1052, -1090]},
        {"line": [1052, -1090, 1041, -979]}
    ],
    [
        {"opacity": 100},
        {"fill": [235, 116, 73]},
        {"stroke": [35, 31, 32]},
        {"strokeWidth": 2},
        {"line": [984, -868, 1204, -868]},
        {"line": [1204, -868, 1204, -979]},
        {"line": [1204, -979, 1041, -979]},
        {"line": [1041, -979, 984, -868]}
    ],
    [
        {"opacity": 100},
        {"fill": [235, 116, 73]},
        {"stroke": [35, 31, 32]},
        {"strokeWidth": 2},
        {"line": [956, -757, 1204, -757]},
        {"line": [1204, -757, 1204, -868]},
        {"line": [1204, -868, 984, -868]},
        {"line": [984, -868, 956, -757]}
    ],
    [
        {"opacity": 100},
        {"fill": [235, 116, 73]},
        {"stroke": [35, 31, 32]},
        {"strokeWidth": 2},
        {"line": [959, -646, 1204, -646]},
        {"line": [1204, -646, 1204, -757]},
        {"line": [1204, -757, 956, -757]},
        {"line": [956, -757, 959, -646]}
    ],
    [
        {"opacity": 100},
        {"fill": [235, 116, 73]},
        {"stroke": [35, 31, 32]},
        {"strokeWidth": 2},
        {"line": [982, -535, 1204, -535]},
        {"line": [1204, -535, 1204, -646]},
        {"line": [1204, -646, 959, -646]},
        {"line": [959, -646, 982, -535]}
    ],
    [
        {"opacity": 100},
        {"fill": [235, 116, 73]},
        {"stroke": [35, 31, 32]},
        {"strokeWidth": 2},
        {"line": [1047, -424, 1204, -424]},
        {"line": [1204, -424, 1204, -535]},
        {"line": [1204, -535, 982, -535]},
        {"line": [982, -535, 1047, -424]}
    ],
    [
        {"opacity": 100},
        {"fill": [235, 116, 73]},
        {"stroke": [35, 31, 32]},
        {"strokeWidth": 2},
        {"line": [1042, -313, 1204, -313]},
        {"line": [1204, -313, 1204, -424]},
        {"line": [1204, -424, 1047, -424]},
        {"line": [1047, -424, 1042, -313]}
    ],
    [
        {"opacity": 100},
        {"fill": [235, 116, 73]},
        {"stroke": [35, 31, 32]},
        {"strokeWidth": 2},
        {"line": [1024, -202, 1204, -202]},
        {"line": [1204, -202, 1204, -313]},
        {"line": [1204, -313, 1042, -313]},
        {"line": [1042, -313, 1024, -202]}
    ],
    [
        {"opacity": 100},
        {"fill": [235, 116, 73]},
        {"stroke": [35, 31, 32]},
        {"strokeWidth": 2},
        {"line": [1042, -91, 1204, -91]},
        {"line": [1204, -91, 1204, -202]},
        {"line": [1204, -202, 1024, -202]},
        {"line": [1024, -202, 1042, -91]}
    ],
    [
        {"opacity": 100},
        {"fill": [235, 116, 73]},
        {"stroke": [35, 31, 32]},
        {"strokeWidth": 2},
        {"line": [1044, 19, 1204, 19]},
        {"line": [1204, 19, 1204, -91]},
        {"line": [1204, -91, 1042, -91]},
        {"line": [1042, -91, 1044, 19]}
    ],
    [
        {"opacity": 100},
        {"fill": [235, 116, 73]},
        {"stroke": [35, 31, 32]},
        {"strokeWidth": 2},
        {"line": [1028, 130, 1204, 130]},
        {"line": [1204, 130, 1204, 19]},
        {"line": [1204, 19, 1044, 19]},
        {"line": [1044, 19, 1028, 130]}
    ],
    [
        {"opacity": 100},
        {"fill": [235, 116, 73]},
        {"stroke": [35, 31, 32]},
        {"strokeWidth": 2},
        {"line": [995, 241, 1204, 241]},
        {"line": [1204, 241, 1204, 130]},
        {"line": [1204, 130, 1028, 130]},
        {"line": [1028, 130, 995, 241]}
    ],
    [
        {"opacity": 100},
        {"fill": [235, 116, 73]},
        {"stroke": [35, 31, 32]},
        {"strokeWidth": 2},
        {"line": [965, 352, 1204, 352]},
        {"line": [1204, 352, 1204, 241]},
        {"line": [1204, 241, 995, 241]},
        {"line": [995, 241, 965, 352]}
    ],
    [
        {"opacity": 100},
        {"fill": [235, 116, 73]},
        {"stroke": [35, 31, 32]},
        {"strokeWidth": 2},
        {"line": [1034, 463, 1204, 463]},
        {"line": [1204, 463, 1204, 352]},
        {"line": [1204, 352, 965, 352]},
        {"line": [965, 352, 1034, 463]}
    ],
    [
        {"opacity": 100},
        {"fill": [235, 116, 73]},
        {"stroke": [35, 31, 32]},
        {"strokeWidth": 2},
        {"line": [1085, 574, 1204, 574]},
        {"line": [1204, 574, 1204, 463]},
        {"line": [1204, 463, 1034, 463]},
        {"line": [1034, 463, 1085, 574]}
    ],
    [
        {"opacity": 100},
        {"fill": [235, 116, 73]},
        {"stroke": [35, 31, 32]},
        {"strokeWidth": 2},
        {"line": [1103, 685, 1204, 685]},
        {"line": [1204, 685, 1204, 574]},
        {"line": [1204, 574, 1085, 574]},
        {"line": [1085, 574, 1103, 685]}
    ],
    [
        {"opacity": 100},
        {"fill": [235, 116, 73]},
        {"stroke": [35, 31, 32]},
        {"strokeWidth": 2},
        {"line": [1097, 796, 1204, 796]},
        {"line": [1204, 796, 1204, 685]},
        {"line": [1204, 685, 1103, 685]},
        {"line": [1103, 685, 1097, 796]}
    ],
    [
        {"opacity": 100},
        {"fill": [235, 116, 73]},
        {"stroke": [35, 31, 32]},
        {"strokeWidth": 2},
        {"line": [1098, 907, 1204, 907]},
        {"line": [1204, 907, 1204, 796]},
        {"line": [1204, 796, 1097, 796]},
        {"line": [1097, 796, 1098, 907]}
    ],
    [
        {"opacity": 100},
        {"fill": [235, 116, 73]},
        {"stroke": [35, 31, 32]},
        {"strokeWidth": 2},
        {"line": [1055, 1018, 1204, 1018]},
        {"line": [1204, 1018, 1204, 907]},
        {"line": [1204, 907, 1098, 907]},
        {"line": [1098, 907, 1055, 1018]}
    ],
    [
        {"opacity": 100},
        {"fill": [235, 116, 73]},
        {"stroke": [35, 31, 32]},
        {"strokeWidth": 2},
        {"line": [969, 1129, 1204, 1129]},
        {"line": [1204, 1129, 1204, 1018]},
        {"line": [1204, 1018, 1055, 1018]},
        {"line": [1055, 1018, 969, 1129]}
    ],
    [
        {"opacity": 100},
        {"fill": [235, 116, 73]},
        {"stroke": [35, 31, 32]},
        {"strokeWidth": 2},
        {"line": [907, 1239, 1204, 1239]},
        {"line": [1204, 1239, 1204, 1129]},
        {"line": [1204, 1129, 969, 1129]},
        {"line": [969, 1129, 907, 1239]}
    ],
    [
        {"opacity": 100},
        {"fill": [235, 116, 73]},
        {"stroke": [35, 31, 32]},
        {"strokeWidth": 2},
        {"line": [947, 1350, 1204, 1350]},
        {"line": [1204, 1350, 1204, 1239]},
        {"line": [1204, 1239, 907, 1239]},
        {"line": [907, 1239, 947, 1350]}
    ],
    [
        {"opacity": 100},
        {"fill": [235, 116, 73]},
        {"stroke": [35, 31, 32]},
        {"strokeWidth": 2},
        {"line": [966, 1461, 1204, 1461]},
        {"line": [1204, 1461, 1204, 1350]},
        {"line": [1204, 1350, 947, 1350]},
        {"line": [947, 1350, 966, 1461]}
    ],
    [
        {"opacity": 100},
        {"fill": [235, 116, 73]},
        {"stroke": [35, 31, 32]},
        {"strokeWidth": 2},
        {"line": [984, 1572, 1204, 1572]},
        {"line": [1204, 1572, 1204, 1461]},
        {"line": [1204, 1461, 966, 1461]},
        {"line": [966, 1461, 984, 1572]}
    ],
    [
        {"opacity": 100},
        {"fill": [235, 116, 73]},
        {"stroke": [35, 31, 32]},
        {"strokeWidth": 2},
        {"line": [1018, 1683, 1204, 1683]},
        {"line": [1204, 1683, 1204, 1572]},
        {"line": [1204, 1572, 984, 1572]},
        {"line": [984, 1572, 1018, 1683]}
    ],
    [
        {"opacity": 100},
        {"fill": [235, 116, 73]},
        {"stroke": [35, 31, 32]},
        {"strokeWidth": 2},
        {"line": [1049, 1794, 1204, 1794]},
        {"line": [1204, 1794, 1204, 1683]},
        {"line": [1204, 1683, 1018, 1683]},
        {"line": [1018, 1683, 1049, 1794]}
    ],
    [
        {"opacity": 100},
        {"fill": [235, 116, 73]},
        {"stroke": [35, 31, 32]},
        {"strokeWidth": 2},
        {"line": [1080, 1905, 1204, 1905]},
        {"line": [1204, 1905, 1204, 1794]},
        {"line": [1204, 1794, 1049, 1794]},
        {"line": [1049, 1794, 1080, 1905]}
    ],
    [
        {"opacity": 100},
        {"fill": [235, 116, 73]},
        {"stroke": [35, 31, 32]},
        {"strokeWidth": 2},
        {"line": [1081, 2016, 1204, 2016]},
        {"line": [1204, 2016, 1204, 1905]},
        {"line": [1204, 1905, 1080, 1905]},
        {"line": [1080, 1905, 1081, 2016]}
    ],
    [
        {"opacity": 100},
        {"fill": [235, 116, 73]},
        {"stroke": [35, 31, 32]},
        {"strokeWidth": 2},
        {"line": [1098, 2127, 1204, 2127]},
        {"line": [1204, 2127, 1204, 2016]},
        {"line": [1204, 2016, 1081, 2016]},
        {"line": [1081, 2016, 1098, 2127]}
    ],
    [
        {"opacity": 100},
        {"fill": [235, 116, 73]},
        {"stroke": [35, 31, 32]},
        {"strokeWidth": 2},
        {"line": [1128, 2238, 1204, 2238]},
        {"line": [1204, 2238, 1204, 2127]},
        {"line": [1204, 2127, 1098, 2127]},
        {"line": [1098, 2127, 1128, 2238]}
    ],
    [
        {"opacity": 100},
        {"fill": [235, 116, 73]},
        {"stroke": [35, 31, 32]},
        {"strokeWidth": 2},
        {"line": [1166, 2349, 1204, 2349]},
        {"line": [1204, 2349, 1204, 2238]},
        {"line": [1204, 2238, 1128, 2238]},
        {"line": [1128, 2238, 1166, 2349]}
    ],
    [
        {"opacity": 100},
        {"fill": [235, 116, 73]},
        {"stroke": [35, 31, 32]},
        {"strokeWidth": 2},
        {"line": [1190, 2460, 1204, 2460]},
        {"line": [1204, 2460, 1204, 2349]},
        {"line": [1204, 2349, 1166, 2349]},
        {"line": [1166, 2349, 1190, 2460]}
    ],
    [
        {"opacity": 100},
        {"fill": [235, 116, 73]},
        {"stroke": [35, 31, 32]},
        {"strokeWidth": 2},
        {"line": [1192, 2571, 1204, 2571]},
        {"line": [1204, 2571, 1204, 2460]},
        {"line": [1204, 2460, 1190, 2460]},
        {"line": [1190, 2460, 1192, 2571]}
    ],
    [
        {"opacity": 100},
        {"fill": [235, 116, 73]},
        {"stroke": [35, 31, 32]},
        {"strokeWidth": 2},
        {"line": [1168, 2682, 1204, 2682]},
        {"line": [1204, 2682, 1204, 2571]},
        {"line": [1204, 2571, 1192, 2571]},
        {"line": [1192, 2571, 1168, 2682]}
    ],
    [
        {"opacity": 100},
        {"fill": [235, 116, 73]},
        {"stroke": [35, 31, 32]},
        {"strokeWidth": 2},
        {"line": [1065, 2793, 1204, 2793]},
        {"line": [1204, 2793, 1204, 2682]},
        {"line": [1204, 2682, 1168, 2682]},
        {"line": [1168, 2682, 1065, 2793]}
    ],
    [
        {"opacity": 100},
        {"fill": [235, 116, 73]},
        {"stroke": [35, 31, 32]},
        {"strokeWidth": 2},
        {"line": [1046, 2904, 1204, 2904]},
        {"line": [1204, 2904, 1204, 2793]},
        {"line": [1204, 2793, 1065, 2793]},
        {"line": [1065, 2793, 1046, 2904]}
    ],
    [
        {"opacity": 100},
        {"fill": [235, 116, 73]},
        {"stroke": [35, 31, 32]},
        {"strokeWidth": 2},
        {"line": [1119, 3015, 1204, 3015]},
        {"line": [1204, 3015, 1204, 2904]},
        {"line": [1204, 2904, 1046, 2904]},
        {"line": [1046, 2904, 1119, 3015]}
    ],
    [
        {"opacity": 100},
        {"fill": [235, 116, 73]},
        {"stroke": [35, 31, 32]},
        {"strokeWidth": 2},
        {"line": [1176, 3126, 1204, 3126]},
        {"line": [1204, 3126, 1204, 3015]},
        {"line": [1204, 3015, 1119, 3015]},
        {"line": [1119, 3015, 1176, 3126]}
    ],
    [
        {"opacity": 100},
        {"fill": [235, 116, 73]},
        {"stroke": [35, 31, 32]},
        {"strokeWidth": 2},
        {"line": [1179, 3237, 1204, 3237]},
        {"line": [1204, 3237, 1204, 3126]},
        {"line": [1204, 3126, 1176, 3126]},
        {"line": [1176, 3126, 1179, 3237]}
    ],
    [
        {"opacity": 100},
        {"fill": [235, 116, 73]},
        {"stroke": [35, 31, 32]},
        {"strokeWidth": 2},
        {"line": [1170, 3348, 1204, 3348]},
        {"line": [1204, 3348, 1204, 3237]},
        {"line": [1204, 3237, 1179, 3237]},
        {"line": [1179, 3237, 1170, 3348]}
    ],
    [
        {"opacity": 100},
        {"fill": [235, 116, 73]},
        {"stroke": [35, 31, 32]},
        {"strokeWidth": 2},
        {"line": [1112, 3459, 1198, 3459]},
        {"line": [1198, 3459, 1204, 3348]},
        {"line": [1204, 3348, 1170, 3348]},
        {"line": [1170, 3348, 1112, 3459]}
    ],
    [
        {"opacity": 100},
        {"fill": [235, 116, 73]},
        {"stroke": [35, 31, 32]},
        {"strokeWidth": 2},
        {"line": [1196, 3570, 1198, 3459]},
        {"line": [1198, 3459, 1112, 3459]},
        {"line": [1112, 3459, 1082, 3570]},
        {"line": [1082, 3570, 1196, 3570]}
    ],
    [
        {"opacity": 100},
        {"fill": [235, 116, 73]},
        {"stroke": [35, 31, 32]},
        {"strokeWidth": 2},
        {"line": [1130, 3681, 1188, 3681]},
        {"line": [1188, 3681, 1196, 3570]},
        {"line": [1196, 3570, 1082, 3570]},
        {"line": [1082, 3570, 1130, 3681]}
    ],
    [
        {"opacity": 100},
        {"fill": [235, 116, 73]},
        {"stroke": [35, 31, 32]},
        {"strokeWidth": 2},
        {"line": [1134, 3792, 1164, 3792]},
        {"line": [1164, 3792, 1188, 3681]},
        {"line": [1188, 3681, 1130, 3681]},
        {"line": [1130, 3681, 1134, 3792]}
    ],
    [
        {"opacity": 100},
        {"fill": [235, 116, 73]},
        {"stroke": [35, 31, 32]},
        {"strokeWidth": 2},
        {"line": [1049, 3903, 1107, 3903]},
        {"line": [1107, 3903, 1164, 3792]},
        {"line": [1164, 3792, 1134, 3792]},
        {"line": [1134, 3792, 1049, 3903]}
    ],
    [
        {"opacity": 100},
        {"fill": [235, 116, 73]},
        {"stroke": [35, 31, 32]},
        {"strokeWidth": 2},
        {"line": [1038, 4014, 1093, 4014]},
        {"line": [1093, 4014, 1107, 3903]},
        {"line": [1107, 3903, 1049, 3903]},
        {"line": [1049, 3903, 1038, 4014]}
    ]
]
