[
    [
        {"opacity": 100},
        {"fill": [144, 167, 164]},
        {"stroke": [35, 31, 32]},
        {"strokeWidth": 2},
        {"line": [-193, -1866, -104, -1756]},
        {"line": [-104, -1756, -47, -1756]},
        {"line": [-47, -1756, -193, -1866]}
    ],
    [
        {"opacity": 100},
        {"fill": [144, 167, 164]},
        {"stroke": [35, 31, 32]},
        {"strokeWidth": 2},
        {"line": [-47, -1756, -104, -1756]},
        {"line": [-104, -1756, -91, -1645]},
        {"line": [-91, -1645, 39, -1645]},
        {"line": [39, -1645, -47, -1756]}
    ],
    [
        {"opacity": 100},
        {"fill": [144, 167, 164]},
        {"stroke": [35, 31, 32]},
        {"strokeWidth": 2},
        {"line": [39, -1645, -91, -1645]},
        {"line": [-91, -1645, -120, -1534]},
        {"line": [-120, -1534, 42, -1534]},
        {"line": [42, -1534, 39, -1645]}
    ],
    [
        {"opacity": 100},
        {"fill": [144, 167, 164]},
        {"stroke": [35, 31, 32]},
        {"strokeWidth": 2},
        {"line": [42, -1534, -120, -1534]},
        {"line": [-120, -1534, -8, -1423]},
        {"line": [-8, -1423, 54, -1423]},
        {"line": [54, -1423, 42, -1534]}
    ],
    [
        {"opacity": 100},
        {"fill": [144, 167, 164]},
        {"stroke": [35, 31, 32]},
        {"strokeWidth": 2},
        {"line": [-8, -1423, 100, -1312]},
        {"line": [100, -1312, 54, -1423]},
        {"line": [54, -1423, -8, -1423]}
    ]
]
